qs_views/apps.py
qs_views/models.py
qs_views/utils.py
django_qs_views-0.0.3.dist-info/LICENSE
django_qs_views-0.0.3.dist-info/METADATA
django_qs_views-0.0.3.dist-info/WHEEL
django_qs_views-0.0.3.dist-info/top_level.txt
django_qs_views-0.0.3.dist-info/RECORD
